odoo/addons/picking_type_confirmation_requirement_rules/README.rst
odoo/addons/picking_type_confirmation_requirement_rules/__init__.py
odoo/addons/picking_type_confirmation_requirement_rules/__manifest__.py
odoo/addons/picking_type_confirmation_requirement_rules/i18n/es.po
odoo/addons/picking_type_confirmation_requirement_rules/models/__init__.py
odoo/addons/picking_type_confirmation_requirement_rules/models/stock_picking.py
odoo/addons/picking_type_confirmation_requirement_rules/models/stock_picking_requirement_rule.py
odoo/addons/picking_type_confirmation_requirement_rules/models/stock_picking_type.py
odoo/addons/picking_type_confirmation_requirement_rules/security/ir.model.access.csv
odoo/addons/picking_type_confirmation_requirement_rules/static/description/icon.png
odoo/addons/picking_type_confirmation_requirement_rules/views/stock_picking_requirement_rule_views.xml
odoo/addons/picking_type_confirmation_requirement_rules/views/stock_picking_views.xml
odoo_addon_picking_type_confirmation_requirement_rules-15.0.1.0.0.1.dist-info/METADATA
odoo_addon_picking_type_confirmation_requirement_rules-15.0.1.0.0.1.dist-info/WHEEL
odoo_addon_picking_type_confirmation_requirement_rules-15.0.1.0.0.1.dist-info/top_level.txt
odoo_addon_picking_type_confirmation_requirement_rules-15.0.1.0.0.1.dist-info/RECORD
